MySEAS/__init__.py
MySEAS/Components/__init__.py
MySEAS/MOEE/MOEC.py
MySEAS/MOEE/MOES.py
MySEAS/MOEE/__init__.py
MySEAS/Setup/IPS.py
MySEAS/Setup/__init__.py
My_SEAS-0.0.3.dist-info/LICENSE
My_SEAS-0.0.3.dist-info/METADATA
My_SEAS-0.0.3.dist-info/WHEEL
My_SEAS-0.0.3.dist-info/top_level.txt
My_SEAS-0.0.3.dist-info/RECORD
