Metadata-Version: 2.1
Name: My-SEAS
Version: 0.0.3
Summary: A Simple Game Engine Libary
Home-page: UNKNOWN
Author: Sixten Bohman
Author-email: Sixten.bohman.08@gmail.com
License: UNKNOWN
Keywords: Python,Game Engine,Game,Engine,Beginner,Education,SEAS,MySEAS
Platform: UNKNOWN
Classifier: Development Status :: 1 - Planning
Classifier: Intended Audience :: Developers
Classifier: Programming Language :: Python :: 3
Classifier: Operating System :: Unix
Classifier: Operating System :: MacOS :: MacOS X
Classifier: Operating System :: Microsoft :: Windows
License-File: LICENSE
Requires-Dist: pygame
Requires-Dist: numpy
